embedding_model/__init__.py
embedding_model/_version.py
embedding_model/api.py
embedding_model/config.py
embedding_model/conversation.py
embedding_model/download.py
embedding_model/io.py
embedding_model/tokenizer.py
embedding_model/cli/adaptive_search.py
embedding_model/cli/benchmark.py
embedding_model/cli/embed.py
embedding_model/cli/search.py
embedding_model/cli/train.py
embedding_model/config/default.yaml
embedding_model/data/__init__.py
embedding_model/data/flatten.py
embedding_model/datasets/__init__.py
embedding_model/datasets/collate.py
embedding_model/datasets/contrastive_text.py
embedding_model/datasets/mixed.py
embedding_model/losses/ntxent.py
embedding_model/model/charcnn.py
embedding_model/train/trainer.py
ppt_json_embedding_model-0.4.1.dist-info/licenses/LICENSE
ppt_json_embedding_model-0.4.1.dist-info/METADATA
ppt_json_embedding_model-0.4.1.dist-info/WHEEL
ppt_json_embedding_model-0.4.1.dist-info/entry_points.txt
ppt_json_embedding_model-0.4.1.dist-info/top_level.txt
ppt_json_embedding_model-0.4.1.dist-info/RECORD
