Metadata-Version: 2.4
Name: ppt-json-embedding-model
Version: 0.4.1
Summary: Open-weight JSON embedding model with CharCNN architecture and contrastive learning - training required
Author: Vicktor Moberg
Maintainer: Team Nazguls - PPT Product Engineering
License: MIT
Project-URL: Repository, https://github.com/ParkPlaceTech/json-embedding-model
Project-URL: Documentation, https://github.com/ParkPlaceTech/json-embedding-model/blob/main/README.md
Project-URL: Issues, https://github.com/ParkPlaceTech/json-embedding-model/issues
Project-URL: Bug Reports, https://github.com/ParkPlaceTech/json-embedding-model/issues
Project-URL: Feature Requests, https://github.com/ParkPlaceTech/json-embedding-model/issues
Classifier: Development Status :: 4 - Beta
Classifier: Intended Audience :: Developers
Classifier: Intended Audience :: Science/Research
Classifier: License :: OSI Approved :: MIT License
Classifier: Topic :: Scientific/Engineering :: Artificial Intelligence
Classifier: Topic :: Software Development :: Libraries :: Python Modules
Classifier: Topic :: Text Processing :: Indexing
Classifier: Programming Language :: Python :: 3
Classifier: Programming Language :: Python :: 3.10
Classifier: Programming Language :: Python :: 3.11
Classifier: Programming Language :: Python :: 3.12
Classifier: Operating System :: OS Independent
Requires-Python: >=3.10
License-File: LICENSE
Requires-Dist: torch>=2.2.0
Requires-Dist: numpy>=1.24.0
Requires-Dist: pyyaml>=6.0.0
Requires-Dist: tqdm>=4.66.0
Requires-Dist: ujson>=5.9.0
Requires-Dist: psutil>=5.8.0
Provides-Extra: dev
Requires-Dist: pytest>=7.0.0; extra == "dev"
Requires-Dist: pytest-cov>=4.0.0; extra == "dev"
Requires-Dist: black>=22.0.0; extra == "dev"
Requires-Dist: isort>=5.0.0; extra == "dev"
Requires-Dist: flake8>=4.0.0; extra == "dev"
Provides-Extra: benchmark
Requires-Dist: matplotlib>=3.5.0; extra == "benchmark"
Requires-Dist: seaborn>=0.11.0; extra == "benchmark"
Requires-Dist: pandas>=1.3.0; extra == "benchmark"
Requires-Dist: scikit-learn>=1.0.0; extra == "benchmark"
Provides-Extra: all
Requires-Dist: ppt-json-embedding-model[benchmark,dev]; extra == "all"
Dynamic: license-file
